xlsx_to_json.py
pyfrigel_db_struct/__init__.py
pyfrigel_db_struct/excel_to_json/__init__.py
pyfrigel_db_struct/excel_to_json/channels.py
pyfrigel_db_struct/excel_to_json/const.py
pyfrigel_db_struct/excel_to_json/excel_to_json.py
pyfrigel_db_struct/excel_to_json/utils.py
pyfrigel_db_struct/tests/__init__.py
pyfrigel_db_struct/tests/test_excel_to_json.py
pyfrigel_db_struct-0.0.3.dist-info/METADATA
pyfrigel_db_struct-0.0.3.dist-info/WHEEL
pyfrigel_db_struct-0.0.3.dist-info/top_level.txt
pyfrigel_db_struct-0.0.3.dist-info/RECORD
