Metadata-Version: 2.4
Name: pyfrigel-db-struct
Version: 0.0.3
Summary: Script collection for creation of DB struct JSON files
Author-email: Artem Piazzi Tsigler <a.piazzi@frigel.com>, Massimo Caverni <m.caverni@frigel.com>
Classifier: Programming Language :: Python :: 3
Classifier: Operating System :: OS Independent
Requires-Python: >=3.8
Requires-Dist: docopt
Requires-Dist: mypy
Requires-Dist: openpyxl
Requires-Dist: openpyxl-stubs
Requires-Dist: pandas
Requires-Dist: pandas-stubs
Requires-Dist: pytest
Requires-Dist: xmltodict
